<?xml version="1.0" encoding="utf-8"?>
<warehouse_shipping_orders xmlns:xsi="http://www.w3.org/2001/XMLSchema-instance" xmlns:xsd="http://www.w3.org/2001/XMLSchema" xmlns="http://www.quorumresources.com">
  <warehouse_shipping_order>
    <account_id>DRCOMFORT</account_id>
    <account_number>66370</account_number>
    <status>N</status>
    <customer_reference_number>10042013</customer_reference_number>
    <consignee_po>PO10042013VA</consignee_po>
    <export>N</export>
    <temperature_controlled>N</temperature_controlled>
    <hazmat>N</hazmat>
    <payment_method>PP</payment_method>
    <transport_method>M</transport_method>
    <scac>DSCE</scac>
    <total_weight>
      <weight>40000</weight>
      <weight_unit_of_measure>LB</weight_unit_of_measure>
    </total_weight>
    <total_volume>
      <volume>2000</volume>
      <volume_unit_of_measure>CF</volume_unit_of_measure>
    </total_volume>
    <shipment_date>20131007</shipment_date>
    <delivery_date>20131008</delivery_date>
    <address>
      <type>SHIPFROM</type>
      <name>EL          </name>
      <address1>21705 MISSISSIPPI STREET           </address1>
      <address2>                                   </address2>
      <city>ELWOOD                        </city>
      <state_province>IL</state_province>
      <postal_code>60421     </postal_code>
    </address>
    <address>
      <type>SHIPTO</type>
      <name>Dr Comfort</name>
      <address1>10300 North Enterprise Drive</address1>
      <address2 xsi:nil="true" />
      <city>Mequon</city>
      <state_province>WI</state_province>
      <postal_code>53092</postal_code>
    </address>
    <ucc128>N</ucc128>
    <order_detail>
      <detail>
        <line_number>1</line_number>
        <product_number_or_nmfc>0010-M-09.0</product_number_or_nmfc>
        <quantity>2</quantity>
      </detail>
      <detail>
        <line_number>2</line_number>
        <product_number_or_nmfc>0010-W-05.5</product_number_or_nmfc>
        <quantity>1</quantity>
      </detail>
      <detail>
        <line_number>3</line_number>
        <product_number_or_nmfc>0010-X-11.0</product_number_or_nmfc>
        <quantity>2</quantity>
      </detail>
      <detail>
        <line_number>4</line_number>
        <product_number_or_nmfc>0040-W-08.0</product_number_or_nmfc>
        <quantity>1</quantity>
      </detail>
      <detail>
        <line_number>5</line_number>
        <product_number_or_nmfc>0040-W-08.5</product_number_or_nmfc>
        <quantity>1</quantity>
      </detail>
      <detail>
        <line_number>6</line_number>
        <product_number_or_nmfc>0040-W-09.0</product_number_or_nmfc>
        <quantity>1</quantity>
      </detail>
      <detail>
        <line_number>7</line_number>
        <product_number_or_nmfc>0040-W-09.5</product_number_or_nmfc>
        <quantity>1</quantity>
      </detail>
      <detail>
        <line_number>8</line_number>
        <product_number_or_nmfc>0810-M-06.0</product_number_or_nmfc>
        <quantity>1</quantity>
      </detail>
      <detail>
        <line_number>9</line_number>
        <product_number_or_nmfc>0810-W-07.5</product_number_or_nmfc>
        <quantity>2</quantity>
      </detail>
      <detail>
        <line_number>10</line_number>
        <product_number_or_nmfc>0810-W-08.5</product_number_or_nmfc>
        <quantity>1</quantity>
      </detail>
      <detail>
        <line_number>11</line_number>
        <product_number_or_nmfc>0820-M-07.0</product_number_or_nmfc>
        <quantity>1</quantity>
      </detail>
      <detail>
        <line_number>12</line_number>
        <product_number_or_nmfc>0820-M-11.0</product_number_or_nmfc>
        <quantity>1</quantity>
      </detail>
      <detail>
        <line_number>13</line_number>
        <product_number_or_nmfc>0820-W-07.0</product_number_or_nmfc>
        <quantity>1</quantity>
      </detail>
      <detail>
        <line_number>14</line_number>
        <product_number_or_nmfc>0820-W-08.5</product_number_or_nmfc>
        <quantity>2</quantity>
      </detail>
      <detail>
        <line_number>15</line_number>
        <product_number_or_nmfc>0820-W-09.0</product_number_or_nmfc>
        <quantity>1</quantity>
      </detail>
      <detail>
        <line_number>16</line_number>
        <product_number_or_nmfc>0820-W-10.0</product_number_or_nmfc>
        <quantity>1</quantity>
      </detail>
      <detail>
        <line_number>17</line_number>
        <product_number_or_nmfc>0820-X-08.0</product_number_or_nmfc>
        <quantity>1</quantity>
      </detail>
      <detail>
        <line_number>18</line_number>
        <product_number_or_nmfc>1040-M-06.5</product_number_or_nmfc>
        <quantity>2</quantity>
      </detail>
      <detail>
        <line_number>19</line_number>
        <product_number_or_nmfc>1040-M-07.0</product_number_or_nmfc>
        <quantity>1</quantity>
      </detail>
      <detail>
        <line_number>20</line_number>
        <product_number_or_nmfc>1040-M-08.0</product_number_or_nmfc>
        <quantity>1</quantity>
      </detail>
      <detail>
        <line_number>21</line_number>
        <product_number_or_nmfc>1040-M-08.5</product_number_or_nmfc>
        <quantity>1</quantity>
      </detail>
      <detail>
        <line_number>22</line_number>
        <product_number_or_nmfc>1040-M-09.0</product_number_or_nmfc>
        <quantity>3</quantity>
      </detail>
      <detail>
        <line_number>23</line_number>
        <product_number_or_nmfc>1040-W-07.0</product_number_or_nmfc>
        <quantity>2</quantity>
      </detail>
      <detail>
        <line_number>24</line_number>
        <product_number_or_nmfc>1040-W-07.5</product_number_or_nmfc>
        <quantity>1</quantity>
      </detail>
      <detail>
        <line_number>25</line_number>
        <product_number_or_nmfc>1040-W-08.0</product_number_or_nmfc>
        <quantity>3</quantity>
      </detail>
      <detail>
        <line_number>26</line_number>
        <product_number_or_nmfc>1040-W-09.0</product_number_or_nmfc>
        <quantity>2</quantity>
      </detail>
      <detail>
        <line_number>27</line_number>
        <product_number_or_nmfc>1040-X-09.5</product_number_or_nmfc>
        <quantity>2</quantity>
      </detail>
      <detail>
        <line_number>28</line_number>
        <product_number_or_nmfc>2010-M-06.0</product_number_or_nmfc>
        <quantity>2</quantity>
      </detail>
      <detail>
        <line_number>29</line_number>
        <product_number_or_nmfc>2010-M-07.5</product_number_or_nmfc>
        <quantity>1</quantity>
      </detail>
      <detail>
        <line_number>30</line_number>
        <product_number_or_nmfc>2010-W-06.5</product_number_or_nmfc>
        <quantity>2</quantity>
      </detail>
      <detail>
        <line_number>31</line_number>
        <product_number_or_nmfc>2030-M-08.5</product_number_or_nmfc>
        <quantity>1</quantity>
      </detail>
      <detail>
        <line_number>32</line_number>
        <product_number_or_nmfc>2030-M-09.5</product_number_or_nmfc>
        <quantity>2</quantity>
      </detail>
      <detail>
        <line_number>33</line_number>
        <product_number_or_nmfc>2030-W-06.5</product_number_or_nmfc>
        <quantity>1</quantity>
      </detail>
      <detail>
        <line_number>34</line_number>
        <product_number_or_nmfc>2030-W-08.5</product_number_or_nmfc>
        <quantity>4</quantity>
      </detail>
      <detail>
        <line_number>35</line_number>
        <product_number_or_nmfc>2030-W-11.0</product_number_or_nmfc>
        <quantity>3</quantity>
      </detail>
      <detail>
        <line_number>36</line_number>
        <product_number_or_nmfc>2030-X-09.0</product_number_or_nmfc>
        <quantity>1</quantity>
      </detail>
      <detail>
        <line_number>37</line_number>
        <product_number_or_nmfc>2030-X-10.0</product_number_or_nmfc>
        <quantity>1</quantity>
      </detail>
      <detail>
        <line_number>38</line_number>
        <product_number_or_nmfc>2040-M-09.5</product_number_or_nmfc>
        <quantity>1</quantity>
      </detail>
      <detail>
        <line_number>39</line_number>
        <product_number_or_nmfc>2040-M-11.0</product_number_or_nmfc>
        <quantity>1</quantity>
      </detail>
      <detail>
        <line_number>40</line_number>
        <product_number_or_nmfc>2040-W-08.0</product_number_or_nmfc>
        <quantity>3</quantity>
      </detail>
      <detail>
        <line_number>41</line_number>
        <product_number_or_nmfc>2040-W-09.0</product_number_or_nmfc>
        <quantity>5</quantity>
      </detail>
      <detail>
        <line_number>42</line_number>
        <product_number_or_nmfc>2040-W-09.5</product_number_or_nmfc>
        <quantity>1</quantity>
      </detail>
      <detail>
        <line_number>43</line_number>
        <product_number_or_nmfc>2040-W-10.0</product_number_or_nmfc>
        <quantity>1</quantity>
      </detail>
      <detail>
        <line_number>44</line_number>
        <product_number_or_nmfc>2040-X-10.0</product_number_or_nmfc>
        <quantity>1</quantity>
      </detail>
      <detail>
        <line_number>45</line_number>
        <product_number_or_nmfc>2105-W-08.0</product_number_or_nmfc>
        <quantity>2</quantity>
      </detail>
      <detail>
        <line_number>46</line_number>
        <product_number_or_nmfc>2105-W-11.0</product_number_or_nmfc>
        <quantity>1</quantity>
      </detail>
      <detail>
        <line_number>47</line_number>
        <product_number_or_nmfc>2110-X-08.0</product_number_or_nmfc>
        <quantity>2</quantity>
      </detail>
      <detail>
        <line_number>48</line_number>
        <product_number_or_nmfc>2210-W-10.0</product_number_or_nmfc>
        <quantity>1</quantity>
      </detail>
      <detail>
        <line_number>49</line_number>
        <product_number_or_nmfc>2210-X-09.0</product_number_or_nmfc>
        <quantity>1</quantity>
      </detail>
      <detail>
        <line_number>50</line_number>
        <product_number_or_nmfc>2230-M-09.0</product_number_or_nmfc>
        <quantity>1</quantity>
      </detail>
      <detail>
        <line_number>51</line_number>
        <product_number_or_nmfc>2230-M-10.5</product_number_or_nmfc>
        <quantity>1</quantity>
      </detail>
      <detail>
        <line_number>52</line_number>
        <product_number_or_nmfc>2230-W-09.0</product_number_or_nmfc>
        <quantity>2</quantity>
      </detail>
      <detail>
        <line_number>53</line_number>
        <product_number_or_nmfc>2230-W-10.0</product_number_or_nmfc>
        <quantity>3</quantity>
      </detail>
      <detail>
        <line_number>54</line_number>
        <product_number_or_nmfc>2245-M-07.0</product_number_or_nmfc>
        <quantity>1</quantity>
      </detail>
      <detail>
        <line_number>55</line_number>
        <product_number_or_nmfc>2245-M-07.5</product_number_or_nmfc>
        <quantity>1</quantity>
      </detail>
      <detail>
        <line_number>56</line_number>
        <product_number_or_nmfc>2245-M-08.5</product_number_or_nmfc>
        <quantity>1</quantity>
      </detail>
      <detail>
        <line_number>57</line_number>
        <product_number_or_nmfc>2245-W-08.5</product_number_or_nmfc>
        <quantity>2</quantity>
      </detail>
      <detail>
        <line_number>58</line_number>
        <product_number_or_nmfc>2245-W-09.5</product_number_or_nmfc>
        <quantity>3</quantity>
      </detail>
      <detail>
        <line_number>59</line_number>
        <product_number_or_nmfc>2310-W-07.5</product_number_or_nmfc>
        <quantity>1</quantity>
      </detail>
      <detail>
        <line_number>60</line_number>
        <product_number_or_nmfc>2315-M-09.0</product_number_or_nmfc>
        <quantity>1</quantity>
      </detail>
      <detail>
        <line_number>61</line_number>
        <product_number_or_nmfc>2315-X-08.0</product_number_or_nmfc>
        <quantity>1</quantity>
      </detail>
      <detail>
        <line_number>62</line_number>
        <product_number_or_nmfc>2440-M-08.5</product_number_or_nmfc>
        <quantity>1</quantity>
      </detail>
      <detail>
        <line_number>63</line_number>
        <product_number_or_nmfc>2440-M-09.5</product_number_or_nmfc>
        <quantity>1</quantity>
      </detail>
      <detail>
        <line_number>64</line_number>
        <product_number_or_nmfc>2440-W-07.0</product_number_or_nmfc>
        <quantity>1</quantity>
      </detail>
      <detail>
        <line_number>65</line_number>
        <product_number_or_nmfc>2440-W-07.5</product_number_or_nmfc>
        <quantity>6</quantity>
      </detail>
      <detail>
        <line_number>66</line_number>
        <product_number_or_nmfc>2440-W-08.0</product_number_or_nmfc>
        <quantity>4</quantity>
      </detail>
      <detail>
        <line_number>67</line_number>
        <product_number_or_nmfc>2440-W-09.5</product_number_or_nmfc>
        <quantity>4</quantity>
      </detail>
      <detail>
        <line_number>68</line_number>
        <product_number_or_nmfc>2440-W-10.0</product_number_or_nmfc>
        <quantity>2</quantity>
      </detail>
      <detail>
        <line_number>69</line_number>
        <product_number_or_nmfc>2440-X-07.5</product_number_or_nmfc>
        <quantity>3</quantity>
      </detail>
      <detail>
        <line_number>70</line_number>
        <product_number_or_nmfc>2440-X-08.0</product_number_or_nmfc>
        <quantity>4</quantity>
      </detail>
      <detail>
        <line_number>71</line_number>
        <product_number_or_nmfc>2440-X-08.5</product_number_or_nmfc>
        <quantity>3</quantity>
      </detail>
      <detail>
        <line_number>72</line_number>
        <product_number_or_nmfc>2440-X-10.0</product_number_or_nmfc>
        <quantity>2</quantity>
      </detail>
      <detail>
        <line_number>73</line_number>
        <product_number_or_nmfc>3110-M-07.5</product_number_or_nmfc>
        <quantity>2</quantity>
      </detail>
      <detail>
        <line_number>74</line_number>
        <product_number_or_nmfc>3110-M-09.0</product_number_or_nmfc>
        <quantity>3</quantity>
      </detail>
      <detail>
        <line_number>75</line_number>
        <product_number_or_nmfc>3110-M-10.0</product_number_or_nmfc>
        <quantity>3</quantity>
      </detail>
      <detail>
        <line_number>76</line_number>
        <product_number_or_nmfc>3110-W-07.5</product_number_or_nmfc>
        <quantity>1</quantity>
      </detail>
      <detail>
        <line_number>77</line_number>
        <product_number_or_nmfc>3110-X-08.5</product_number_or_nmfc>
        <quantity>1</quantity>
      </detail>
      <detail>
        <line_number>78</line_number>
        <product_number_or_nmfc>3140-M-07.5</product_number_or_nmfc>
        <quantity>3</quantity>
      </detail>
      <detail>
        <line_number>79</line_number>
        <product_number_or_nmfc>3140-M-08.5</product_number_or_nmfc>
        <quantity>2</quantity>
      </detail>
      <detail>
        <line_number>80</line_number>
        <product_number_or_nmfc>3140-M-09.5</product_number_or_nmfc>
        <quantity>5</quantity>
      </detail>
      <detail>
        <line_number>81</line_number>
        <product_number_or_nmfc>3140-W-07.5</product_number_or_nmfc>
        <quantity>1</quantity>
      </detail>
      <detail>
        <line_number>82</line_number>
        <product_number_or_nmfc>3140-W-08.0</product_number_or_nmfc>
        <quantity>1</quantity>
      </detail>
      <detail>
        <line_number>83</line_number>
        <product_number_or_nmfc>3140-W-08.5</product_number_or_nmfc>
        <quantity>7</quantity>
      </detail>
      <detail>
        <line_number>84</line_number>
        <product_number_or_nmfc>3140-W-09.0</product_number_or_nmfc>
        <quantity>1</quantity>
      </detail>
      <detail>
        <line_number>85</line_number>
        <product_number_or_nmfc>3140-W-09.5</product_number_or_nmfc>
        <quantity>4</quantity>
      </detail>
      <detail>
        <line_number>86</line_number>
        <product_number_or_nmfc>3140-W-10.0</product_number_or_nmfc>
        <quantity>1</quantity>
      </detail>
      <detail>
        <line_number>87</line_number>
        <product_number_or_nmfc>3140-W-10.5</product_number_or_nmfc>
        <quantity>1</quantity>
      </detail>
      <detail>
        <line_number>88</line_number>
        <product_number_or_nmfc>3140-W-11.0</product_number_or_nmfc>
        <quantity>3</quantity>
      </detail>
      <detail>
        <line_number>89</line_number>
        <product_number_or_nmfc>3140-X-08.5</product_number_or_nmfc>
        <quantity>1</quantity>
      </detail>
      <detail>
        <line_number>90</line_number>
        <product_number_or_nmfc>3210-M-06.5</product_number_or_nmfc>
        <quantity>1</quantity>
      </detail>
      <detail>
        <line_number>91</line_number>
        <product_number_or_nmfc>3210-M-08.5</product_number_or_nmfc>
        <quantity>2</quantity>
      </detail>
      <detail>
        <line_number>92</line_number>
        <product_number_or_nmfc>3210-W-06.0</product_number_or_nmfc>
        <quantity>1</quantity>
      </detail>
      <detail>
        <line_number>93</line_number>
        <product_number_or_nmfc>3210-X-06.0</product_number_or_nmfc>
        <quantity>1</quantity>
      </detail>
      <detail>
        <line_number>94</line_number>
        <product_number_or_nmfc>3210-X-10.5</product_number_or_nmfc>
        <quantity>1</quantity>
      </detail>
      <detail>
        <line_number>95</line_number>
        <product_number_or_nmfc>3240-M-07.5</product_number_or_nmfc>
        <quantity>2</quantity>
      </detail>
      <detail>
        <line_number>96</line_number>
        <product_number_or_nmfc>3240-M-10.0</product_number_or_nmfc>
        <quantity>1</quantity>
      </detail>
      <detail>
        <line_number>97</line_number>
        <product_number_or_nmfc>3240-M-12.0</product_number_or_nmfc>
        <quantity>2</quantity>
      </detail>
      <detail>
        <line_number>98</line_number>
        <product_number_or_nmfc>3240-W-05.0</product_number_or_nmfc>
        <quantity>1</quantity>
      </detail>
      <detail>
        <line_number>99</line_number>
        <product_number_or_nmfc>3240-W-07.0</product_number_or_nmfc>
        <quantity>1</quantity>
      </detail>
      <detail>
        <line_number>100</line_number>
        <product_number_or_nmfc>3240-W-08.0</product_number_or_nmfc>
        <quantity>16</quantity>
      </detail>
      <detail>
        <line_number>101</line_number>
        <product_number_or_nmfc>3240-W-11.0</product_number_or_nmfc>
        <quantity>1</quantity>
      </detail>
      <detail>
        <line_number>102</line_number>
        <product_number_or_nmfc>3240-X-07.5</product_number_or_nmfc>
        <quantity>1</quantity>
      </detail>
      <detail>
        <line_number>103</line_number>
        <product_number_or_nmfc>3240-X-08.5</product_number_or_nmfc>
        <quantity>3</quantity>
      </detail>
      <detail>
        <line_number>104</line_number>
        <product_number_or_nmfc>3240-X-09.5</product_number_or_nmfc>
        <quantity>1</quantity>
      </detail>
      <detail>
        <line_number>105</line_number>
        <product_number_or_nmfc>3240-X-10.0</product_number_or_nmfc>
        <quantity>2</quantity>
      </detail>
      <detail>
        <line_number>106</line_number>
        <product_number_or_nmfc>3240-X-10.5</product_number_or_nmfc>
        <quantity>1</quantity>
      </detail>
      <detail>
        <line_number>107</line_number>
        <product_number_or_nmfc>3240-X-11.0</product_number_or_nmfc>
        <quantity>1</quantity>
      </detail>
      <detail>
        <line_number>108</line_number>
        <product_number_or_nmfc>3340-M-06.5</product_number_or_nmfc>
        <quantity>1</quantity>
      </detail>
      <detail>
        <line_number>109</line_number>
        <product_number_or_nmfc>3340-M-07.0</product_number_or_nmfc>
        <quantity>2</quantity>
      </detail>
      <detail>
        <line_number>110</line_number>
        <product_number_or_nmfc>3340-M-08.0</product_number_or_nmfc>
        <quantity>3</quantity>
      </detail>
      <detail>
        <line_number>111</line_number>
        <product_number_or_nmfc>3340-M-08.5</product_number_or_nmfc>
        <quantity>1</quantity>
      </detail>
      <detail>
        <line_number>112</line_number>
        <product_number_or_nmfc>3340-M-09.0</product_number_or_nmfc>
        <quantity>2</quantity>
      </detail>
      <detail>
        <line_number>113</line_number>
        <product_number_or_nmfc>3340-M-09.5</product_number_or_nmfc>
        <quantity>1</quantity>
      </detail>
      <detail>
        <line_number>114</line_number>
        <product_number_or_nmfc>3340-M-10.0</product_number_or_nmfc>
        <quantity>2</quantity>
      </detail>
      <detail>
        <line_number>115</line_number>
        <product_number_or_nmfc>3340-M-12.0</product_number_or_nmfc>
        <quantity>1</quantity>
      </detail>
      <detail>
        <line_number>116</line_number>
        <product_number_or_nmfc>3340-W-08.5</product_number_or_nmfc>
        <quantity>7</quantity>
      </detail>
      <detail>
        <line_number>117</line_number>
        <product_number_or_nmfc>3340-W-09.0</product_number_or_nmfc>
        <quantity>5</quantity>
      </detail>
      <detail>
        <line_number>118</line_number>
        <product_number_or_nmfc>3340-W-09.5</product_number_or_nmfc>
        <quantity>2</quantity>
      </detail>
      <detail>
        <line_number>119</line_number>
        <product_number_or_nmfc>3340-W-10.0</product_number_or_nmfc>
        <quantity>4</quantity>
      </detail>
      <detail>
        <line_number>120</line_number>
        <product_number_or_nmfc>3340-W-12.0</product_number_or_nmfc>
        <quantity>3</quantity>
      </detail>
      <detail>
        <line_number>121</line_number>
        <product_number_or_nmfc>3340-X-08.5</product_number_or_nmfc>
        <quantity>3</quantity>
      </detail>
      <detail>
        <line_number>122</line_number>
        <product_number_or_nmfc>3340-X-09.0</product_number_or_nmfc>
        <quantity>1</quantity>
      </detail>
      <detail>
        <line_number>123</line_number>
        <product_number_or_nmfc>3340-X-09.5</product_number_or_nmfc>
        <quantity>3</quantity>
      </detail>
      <detail>
        <line_number>124</line_number>
        <product_number_or_nmfc>3340-X-10.0</product_number_or_nmfc>
        <quantity>2</quantity>
      </detail>
      <detail>
        <line_number>125</line_number>
        <product_number_or_nmfc>3350-M-07.5</product_number_or_nmfc>
        <quantity>3</quantity>
      </detail>
      <detail>
        <line_number>126</line_number>
        <product_number_or_nmfc>3350-M-08.0</product_number_or_nmfc>
        <quantity>2</quantity>
      </detail>
      <detail>
        <line_number>127</line_number>
        <product_number_or_nmfc>3350-M-09.5</product_number_or_nmfc>
        <quantity>2</quantity>
      </detail>
      <detail>
        <line_number>128</line_number>
        <product_number_or_nmfc>3350-M-10.0</product_number_or_nmfc>
        <quantity>3</quantity>
      </detail>
      <detail>
        <line_number>129</line_number>
        <product_number_or_nmfc>3350-W-06.0</product_number_or_nmfc>
        <quantity>3</quantity>
      </detail>
      <detail>
        <line_number>130</line_number>
        <product_number_or_nmfc>3350-W-06.5</product_number_or_nmfc>
        <quantity>2</quantity>
      </detail>
      <detail>
        <line_number>131</line_number>
        <product_number_or_nmfc>3350-W-07.0</product_number_or_nmfc>
        <quantity>4</quantity>
      </detail>
      <detail>
        <line_number>132</line_number>
        <product_number_or_nmfc>3350-W-08.5</product_number_or_nmfc>
        <quantity>4</quantity>
      </detail>
      <detail>
        <line_number>133</line_number>
        <product_number_or_nmfc>3350-W-09.0</product_number_or_nmfc>
        <quantity>3</quantity>
      </detail>
      <detail>
        <line_number>134</line_number>
        <product_number_or_nmfc>3350-W-10.0</product_number_or_nmfc>
        <quantity>1</quantity>
      </detail>
      <detail>
        <line_number>135</line_number>
        <product_number_or_nmfc>3350-W-10.5</product_number_or_nmfc>
        <quantity>2</quantity>
      </detail>
      <detail>
        <line_number>136</line_number>
        <product_number_or_nmfc>3350-W-11.0</product_number_or_nmfc>
        <quantity>1</quantity>
      </detail>
      <detail>
        <line_number>137</line_number>
        <product_number_or_nmfc>3350-X-08.5</product_number_or_nmfc>
        <quantity>1</quantity>
      </detail>
      <detail>
        <line_number>138</line_number>
        <product_number_or_nmfc>3350-X-10.0</product_number_or_nmfc>
        <quantity>3</quantity>
      </detail>
      <detail>
        <line_number>139</line_number>
        <product_number_or_nmfc>3350-X-11.0</product_number_or_nmfc>
        <quantity>1</quantity>
      </detail>
      <detail>
        <line_number>140</line_number>
        <product_number_or_nmfc>3370-M-06.0</product_number_or_nmfc>
        <quantity>1</quantity>
      </detail>
      <detail>
        <line_number>141</line_number>
        <product_number_or_nmfc>3370-M-07.0</product_number_or_nmfc>
        <quantity>2</quantity>
      </detail>
      <detail>
        <line_number>142</line_number>
        <product_number_or_nmfc>3370-M-08.0</product_number_or_nmfc>
        <quantity>3</quantity>
      </detail>
      <detail>
        <line_number>143</line_number>
        <product_number_or_nmfc>3370-M-09.0</product_number_or_nmfc>
        <quantity>2</quantity>
      </detail>
      <detail>
        <line_number>144</line_number>
        <product_number_or_nmfc>3370-M-09.5</product_number_or_nmfc>
        <quantity>2</quantity>
      </detail>
      <detail>
        <line_number>145</line_number>
        <product_number_or_nmfc>3370-M-10.5</product_number_or_nmfc>
        <quantity>3</quantity>
      </detail>
      <detail>
        <line_number>146</line_number>
        <product_number_or_nmfc>3370-W-08.0</product_number_or_nmfc>
        <quantity>5</quantity>
      </detail>
      <detail>
        <line_number>147</line_number>
        <product_number_or_nmfc>3370-W-10.0</product_number_or_nmfc>
        <quantity>2</quantity>
      </detail>
      <detail>
        <line_number>148</line_number>
        <product_number_or_nmfc>3370-W-11.0</product_number_or_nmfc>
        <quantity>1</quantity>
      </detail>
      <detail>
        <line_number>149</line_number>
        <product_number_or_nmfc>3370-X-09.0</product_number_or_nmfc>
        <quantity>2</quantity>
      </detail>
      <detail>
        <line_number>150</line_number>
        <product_number_or_nmfc>3440-M-07.5</product_number_or_nmfc>
        <quantity>2</quantity>
      </detail>
      <detail>
        <line_number>151</line_number>
        <product_number_or_nmfc>3440-M-08.0</product_number_or_nmfc>
        <quantity>1</quantity>
      </detail>
      <detail>
        <line_number>152</line_number>
        <product_number_or_nmfc>3440-M-08.5</product_number_or_nmfc>
        <quantity>2</quantity>
      </detail>
      <detail>
        <line_number>153</line_number>
        <product_number_or_nmfc>3440-M-09.0</product_number_or_nmfc>
        <quantity>2</quantity>
      </detail>
      <detail>
        <line_number>154</line_number>
        <product_number_or_nmfc>3440-M-10.0</product_number_or_nmfc>
        <quantity>2</quantity>
      </detail>
      <detail>
        <line_number>155</line_number>
        <product_number_or_nmfc>3440-M-11.0</product_number_or_nmfc>
        <quantity>1</quantity>
      </detail>
      <detail>
        <line_number>156</line_number>
        <product_number_or_nmfc>3440-W-07.0</product_number_or_nmfc>
        <quantity>1</quantity>
      </detail>
      <detail>
        <line_number>157</line_number>
        <product_number_or_nmfc>3440-W-09.0</product_number_or_nmfc>
        <quantity>4</quantity>
      </detail>
      <detail>
        <line_number>158</line_number>
        <product_number_or_nmfc>3440-W-11.0</product_number_or_nmfc>
        <quantity>1</quantity>
      </detail>
      <detail>
        <line_number>159</line_number>
        <product_number_or_nmfc>3440-X-08.0</product_number_or_nmfc>
        <quantity>1</quantity>
      </detail>
      <detail>
        <line_number>160</line_number>
        <product_number_or_nmfc>3440-X-08.5</product_number_or_nmfc>
        <quantity>1</quantity>
      </detail>
      <detail>
        <line_number>161</line_number>
        <product_number_or_nmfc>3450-M-07.5</product_number_or_nmfc>
        <quantity>1</quantity>
      </detail>
      <detail>
        <line_number>162</line_number>
        <product_number_or_nmfc>3450-M-09.0</product_number_or_nmfc>
        <quantity>2</quantity>
      </detail>
      <detail>
        <line_number>163</line_number>
        <product_number_or_nmfc>3450-M-09.5</product_number_or_nmfc>
        <quantity>1</quantity>
      </detail>
      <detail>
        <line_number>164</line_number>
        <product_number_or_nmfc>3450-M-11.0</product_number_or_nmfc>
        <quantity>1</quantity>
      </detail>
      <detail>
        <line_number>165</line_number>
        <product_number_or_nmfc>3450-W-06.0</product_number_or_nmfc>
        <quantity>1</quantity>
      </detail>
      <detail>
        <line_number>166</line_number>
        <product_number_or_nmfc>3450-X-06.0</product_number_or_nmfc>
        <quantity>1</quantity>
      </detail>
      <detail>
        <line_number>167</line_number>
        <product_number_or_nmfc>3450-X-07.5</product_number_or_nmfc>
        <quantity>3</quantity>
      </detail>
      <detail>
        <line_number>168</line_number>
        <product_number_or_nmfc>3470-M-07.5</product_number_or_nmfc>
        <quantity>2</quantity>
      </detail>
      <detail>
        <line_number>169</line_number>
        <product_number_or_nmfc>3470-M-08.0</product_number_or_nmfc>
        <quantity>2</quantity>
      </detail>
      <detail>
        <line_number>170</line_number>
        <product_number_or_nmfc>3470-M-08.5</product_number_or_nmfc>
        <quantity>1</quantity>
      </detail>
      <detail>
        <line_number>171</line_number>
        <product_number_or_nmfc>3470-M-09.0</product_number_or_nmfc>
        <quantity>1</quantity>
      </detail>
      <detail>
        <line_number>172</line_number>
        <product_number_or_nmfc>3470-W-06.5</product_number_or_nmfc>
        <quantity>2</quantity>
      </detail>
      <detail>
        <line_number>173</line_number>
        <product_number_or_nmfc>3470-X-06.0</product_number_or_nmfc>
        <quantity>1</quantity>
      </detail>
      <detail>
        <line_number>174</line_number>
        <product_number_or_nmfc>3470-X-07.0</product_number_or_nmfc>
        <quantity>2</quantity>
      </detail>
      <detail>
        <line_number>175</line_number>
        <product_number_or_nmfc>3470-X-09.0</product_number_or_nmfc>
        <quantity>2</quantity>
      </detail>
      <detail>
        <line_number>176</line_number>
        <product_number_or_nmfc>3820-X-06.0</product_number_or_nmfc>
        <quantity>1</quantity>
      </detail>
      <detail>
        <line_number>177</line_number>
        <product_number_or_nmfc>4020-W-06.0</product_number_or_nmfc>
        <quantity>1</quantity>
      </detail>
      <detail>
        <line_number>178</line_number>
        <product_number_or_nmfc>4210-X-08.0</product_number_or_nmfc>
        <quantity>1</quantity>
      </detail>
      <detail>
        <line_number>179</line_number>
        <product_number_or_nmfc>4240-W-07.0</product_number_or_nmfc>
        <quantity>1</quantity>
      </detail>
      <detail>
        <line_number>180</line_number>
        <product_number_or_nmfc>4270-W-08.0</product_number_or_nmfc>
        <quantity>2</quantity>
      </detail>
      <detail>
        <line_number>181</line_number>
        <product_number_or_nmfc>4270-W-10.5</product_number_or_nmfc>
        <quantity>1</quantity>
      </detail>
      <detail>
        <line_number>182</line_number>
        <product_number_or_nmfc>4270-W-11.0</product_number_or_nmfc>
        <quantity>1</quantity>
      </detail>
      <detail>
        <line_number>183</line_number>
        <product_number_or_nmfc>4415-M-08.0</product_number_or_nmfc>
        <quantity>1</quantity>
      </detail>
      <detail>
        <line_number>184</line_number>
        <product_number_or_nmfc>4415-W-07.5</product_number_or_nmfc>
        <quantity>3</quantity>
      </detail>
      <detail>
        <line_number>185</line_number>
        <product_number_or_nmfc>4415-W-09.5</product_number_or_nmfc>
        <quantity>4</quantity>
      </detail>
      <detail>
        <line_number>186</line_number>
        <product_number_or_nmfc>4415-X-07.5</product_number_or_nmfc>
        <quantity>1</quantity>
      </detail>
      <detail>
        <line_number>187</line_number>
        <product_number_or_nmfc>4430-M-08.0</product_number_or_nmfc>
        <quantity>1</quantity>
      </detail>
      <detail>
        <line_number>188</line_number>
        <product_number_or_nmfc>4430-M-08.5</product_number_or_nmfc>
        <quantity>1</quantity>
      </detail>
      <detail>
        <line_number>189</line_number>
        <product_number_or_nmfc>4430-W-06.0</product_number_or_nmfc>
        <quantity>1</quantity>
      </detail>
      <detail>
        <line_number>190</line_number>
        <product_number_or_nmfc>4430-W-07.0</product_number_or_nmfc>
        <quantity>1</quantity>
      </detail>
      <detail>
        <line_number>191</line_number>
        <product_number_or_nmfc>4430-W-09.0</product_number_or_nmfc>
        <quantity>1</quantity>
      </detail>
      <detail>
        <line_number>192</line_number>
        <product_number_or_nmfc>4510-W-05.5</product_number_or_nmfc>
        <quantity>1</quantity>
      </detail>
      <detail>
        <line_number>193</line_number>
        <product_number_or_nmfc>4530-M-08.5</product_number_or_nmfc>
        <quantity>1</quantity>
      </detail>
      <detail>
        <line_number>194</line_number>
        <product_number_or_nmfc>4530-W-06.5</product_number_or_nmfc>
        <quantity>1</quantity>
      </detail>
      <detail>
        <line_number>195</line_number>
        <product_number_or_nmfc>4530-W-07.0</product_number_or_nmfc>
        <quantity>2</quantity>
      </detail>
      <detail>
        <line_number>196</line_number>
        <product_number_or_nmfc>4530-W-08.5</product_number_or_nmfc>
        <quantity>2</quantity>
      </detail>
      <detail>
        <line_number>197</line_number>
        <product_number_or_nmfc>4530-W-11.0</product_number_or_nmfc>
        <quantity>1</quantity>
      </detail>
      <detail>
        <line_number>198</line_number>
        <product_number_or_nmfc>4530-X-07.0</product_number_or_nmfc>
        <quantity>1</quantity>
      </detail>
      <detail>
        <line_number>199</line_number>
        <product_number_or_nmfc>4530-X-08.5</product_number_or_nmfc>
        <quantity>1</quantity>
      </detail>
      <detail>
        <line_number>200</line_number>
        <product_number_or_nmfc>4610-W-09.5</product_number_or_nmfc>
        <quantity>2</quantity>
      </detail>
      <detail>
        <line_number>201</line_number>
        <product_number_or_nmfc>4620-M-05.5</product_number_or_nmfc>
        <quantity>1</quantity>
      </detail>
      <detail>
        <line_number>202</line_number>
        <product_number_or_nmfc>4620-M-06.5</product_number_or_nmfc>
        <quantity>1</quantity>
      </detail>
      <detail>
        <line_number>203</line_number>
        <product_number_or_nmfc>4630-W-07.0</product_number_or_nmfc>
        <quantity>1</quantity>
      </detail>
      <detail>
        <line_number>204</line_number>
        <product_number_or_nmfc>4735-M-07.5</product_number_or_nmfc>
        <quantity>1</quantity>
      </detail>
      <detail>
        <line_number>205</line_number>
        <product_number_or_nmfc>4910-M-08.0</product_number_or_nmfc>
        <quantity>1</quantity>
      </detail>
      <detail>
        <line_number>206</line_number>
        <product_number_or_nmfc>4910-M-10.0</product_number_or_nmfc>
        <quantity>1</quantity>
      </detail>
      <detail>
        <line_number>207</line_number>
        <product_number_or_nmfc>4910-W-10.0</product_number_or_nmfc>
        <quantity>1</quantity>
      </detail>
      <detail>
        <line_number>208</line_number>
        <product_number_or_nmfc>4910-X-06.5</product_number_or_nmfc>
        <quantity>1</quantity>
      </detail>
      <detail>
        <line_number>209</line_number>
        <product_number_or_nmfc>4910-X-07.0</product_number_or_nmfc>
        <quantity>2</quantity>
      </detail>
      <detail>
        <line_number>210</line_number>
        <product_number_or_nmfc>4910-X-07.5</product_number_or_nmfc>
        <quantity>2</quantity>
      </detail>
      <detail>
        <line_number>211</line_number>
        <product_number_or_nmfc>4910-X-11.0</product_number_or_nmfc>
        <quantity>2</quantity>
      </detail>
      <detail>
        <line_number>212</line_number>
        <product_number_or_nmfc>4930-W-07.5</product_number_or_nmfc>
        <quantity>1</quantity>
      </detail>
      <detail>
        <line_number>213</line_number>
        <product_number_or_nmfc>4930-W-08.0</product_number_or_nmfc>
        <quantity>1</quantity>
      </detail>
      <detail>
        <line_number>214</line_number>
        <product_number_or_nmfc>4930-X-06.5</product_number_or_nmfc>
        <quantity>1</quantity>
      </detail>
      <detail>
        <line_number>215</line_number>
        <product_number_or_nmfc>4930-X-07.5</product_number_or_nmfc>
        <quantity>1</quantity>
      </detail>
      <detail>
        <line_number>216</line_number>
        <product_number_or_nmfc>4930-X-09.0</product_number_or_nmfc>
        <quantity>2</quantity>
      </detail>
      <detail>
        <line_number>217</line_number>
        <product_number_or_nmfc>4930-X-10.0</product_number_or_nmfc>
        <quantity>2</quantity>
      </detail>
      <detail>
        <line_number>218</line_number>
        <product_number_or_nmfc>848270002061</product_number_or_nmfc>
        <quantity>5</quantity>
      </detail>
      <detail>
        <line_number>219</line_number>
        <product_number_or_nmfc>848270002085</product_number_or_nmfc>
        <quantity>6</quantity>
      </detail>
      <detail>
        <line_number>220</line_number>
        <product_number_or_nmfc>5520-M-08.5</product_number_or_nmfc>
        <quantity>1</quantity>
      </detail>
      <detail>
        <line_number>221</line_number>
        <product_number_or_nmfc>6110-M-11.0</product_number_or_nmfc>
        <quantity>2</quantity>
      </detail>
      <detail>
        <line_number>222</line_number>
        <product_number_or_nmfc>6110-X-08.0</product_number_or_nmfc>
        <quantity>1</quantity>
      </detail>
      <detail>
        <line_number>223</line_number>
        <product_number_or_nmfc>6110-X-08.5</product_number_or_nmfc>
        <quantity>2</quantity>
      </detail>
      <detail>
        <line_number>224</line_number>
        <product_number_or_nmfc>6110-X-10.5</product_number_or_nmfc>
        <quantity>1</quantity>
      </detail>
      <detail>
        <line_number>225</line_number>
        <product_number_or_nmfc>6110-X-11.5</product_number_or_nmfc>
        <quantity>1</quantity>
      </detail>
      <detail>
        <line_number>226</line_number>
        <product_number_or_nmfc>6110-X-13.0</product_number_or_nmfc>
        <quantity>2</quantity>
      </detail>
      <detail>
        <line_number>227</line_number>
        <product_number_or_nmfc>6310-X-08.0</product_number_or_nmfc>
        <quantity>5</quantity>
      </detail>
      <detail>
        <line_number>228</line_number>
        <product_number_or_nmfc>6310-X-08.5</product_number_or_nmfc>
        <quantity>7</quantity>
      </detail>
      <detail>
        <line_number>229</line_number>
        <product_number_or_nmfc>6310-X-09.0</product_number_or_nmfc>
        <quantity>8</quantity>
      </detail>
      <detail>
        <line_number>230</line_number>
        <product_number_or_nmfc>6310-X-09.5</product_number_or_nmfc>
        <quantity>5</quantity>
      </detail>
      <detail>
        <line_number>231</line_number>
        <product_number_or_nmfc>6510-W-06.0</product_number_or_nmfc>
        <quantity>1</quantity>
      </detail>
      <detail>
        <line_number>232</line_number>
        <product_number_or_nmfc>6510-W-07.0</product_number_or_nmfc>
        <quantity>1</quantity>
      </detail>
      <detail>
        <line_number>233</line_number>
        <product_number_or_nmfc>6510-X-07.0</product_number_or_nmfc>
        <quantity>3</quantity>
      </detail>
      <detail>
        <line_number>234</line_number>
        <product_number_or_nmfc>6520-W-08.0</product_number_or_nmfc>
        <quantity>2</quantity>
      </detail>
      <detail>
        <line_number>235</line_number>
        <product_number_or_nmfc>6520-W-09.0</product_number_or_nmfc>
        <quantity>2</quantity>
      </detail>
      <detail>
        <line_number>236</line_number>
        <product_number_or_nmfc>6710-M-07.0</product_number_or_nmfc>
        <quantity>1</quantity>
      </detail>
      <detail>
        <line_number>237</line_number>
        <product_number_or_nmfc>6710-X-07.0</product_number_or_nmfc>
        <quantity>2</quantity>
      </detail>
      <detail>
        <line_number>238</line_number>
        <product_number_or_nmfc>6740-M-09.5</product_number_or_nmfc>
        <quantity>1</quantity>
      </detail>
      <detail>
        <line_number>239</line_number>
        <product_number_or_nmfc>6740-M-10.0</product_number_or_nmfc>
        <quantity>1</quantity>
      </detail>
      <detail>
        <line_number>240</line_number>
        <product_number_or_nmfc>6740-M-13.0</product_number_or_nmfc>
        <quantity>2</quantity>
      </detail>
      <detail>
        <line_number>241</line_number>
        <product_number_or_nmfc>6740-W-08.0</product_number_or_nmfc>
        <quantity>1</quantity>
      </detail>
      <detail>
        <line_number>242</line_number>
        <product_number_or_nmfc>6740-W-10.5</product_number_or_nmfc>
        <quantity>4</quantity>
      </detail>
      <detail>
        <line_number>243</line_number>
        <product_number_or_nmfc>6740-X-10.5</product_number_or_nmfc>
        <quantity>2</quantity>
      </detail>
      <detail>
        <line_number>244</line_number>
        <product_number_or_nmfc>6810-M-11.0</product_number_or_nmfc>
        <quantity>1</quantity>
      </detail>
      <detail>
        <line_number>245</line_number>
        <product_number_or_nmfc>6810-W-10.0</product_number_or_nmfc>
        <quantity>3</quantity>
      </detail>
      <detail>
        <line_number>246</line_number>
        <product_number_or_nmfc>6810-W-10.5</product_number_or_nmfc>
        <quantity>8</quantity>
      </detail>
      <detail>
        <line_number>247</line_number>
        <product_number_or_nmfc>6810-W-12.0</product_number_or_nmfc>
        <quantity>2</quantity>
      </detail>
      <detail>
        <line_number>248</line_number>
        <product_number_or_nmfc>6810-X-08.0</product_number_or_nmfc>
        <quantity>1</quantity>
      </detail>
      <detail>
        <line_number>249</line_number>
        <product_number_or_nmfc>6810-X-10.0</product_number_or_nmfc>
        <quantity>1</quantity>
      </detail>
      <detail>
        <line_number>250</line_number>
        <product_number_or_nmfc>6810-X-10.5</product_number_or_nmfc>
        <quantity>2</quantity>
      </detail>
      <detail>
        <line_number>251</line_number>
        <product_number_or_nmfc>6810-X-11.0</product_number_or_nmfc>
        <quantity>1</quantity>
      </detail>
      <detail>
        <line_number>252</line_number>
        <product_number_or_nmfc>6810-X-11.5</product_number_or_nmfc>
        <quantity>2</quantity>
      </detail>
      <detail>
        <line_number>253</line_number>
        <product_number_or_nmfc>6810-X-13.0</product_number_or_nmfc>
        <quantity>1</quantity>
      </detail>
      <detail>
        <line_number>254</line_number>
        <product_number_or_nmfc>6840-M-08.0</product_number_or_nmfc>
        <quantity>1</quantity>
      </detail>
      <detail>
        <line_number>255</line_number>
        <product_number_or_nmfc>6840-M-09.5</product_number_or_nmfc>
        <quantity>1</quantity>
      </detail>
      <detail>
        <line_number>256</line_number>
        <product_number_or_nmfc>6840-M-10.5</product_number_or_nmfc>
        <quantity>1</quantity>
      </detail>
      <detail>
        <line_number>257</line_number>
        <product_number_or_nmfc>6840-M-13.0</product_number_or_nmfc>
        <quantity>1</quantity>
      </detail>
      <detail>
        <line_number>258</line_number>
        <product_number_or_nmfc>6840-W-10.5</product_number_or_nmfc>
        <quantity>8</quantity>
      </detail>
      <detail>
        <line_number>259</line_number>
        <product_number_or_nmfc>6840-X-08.5</product_number_or_nmfc>
        <quantity>2</quantity>
      </detail>
      <detail>
        <line_number>260</line_number>
        <product_number_or_nmfc>6840-X-10.0</product_number_or_nmfc>
        <quantity>1</quantity>
      </detail>
      <detail>
        <line_number>261</line_number>
        <product_number_or_nmfc>6840-X-11.5</product_number_or_nmfc>
        <quantity>1</quantity>
      </detail>
      <detail>
        <line_number>262</line_number>
        <product_number_or_nmfc>6920-M-06.0</product_number_or_nmfc>
        <quantity>1</quantity>
      </detail>
      <detail>
        <line_number>263</line_number>
        <product_number_or_nmfc>6920-X-10.0</product_number_or_nmfc>
        <quantity>3</quantity>
      </detail>
      <detail>
        <line_number>264</line_number>
        <product_number_or_nmfc>7210-M-09.5</product_number_or_nmfc>
        <quantity>2</quantity>
      </detail>
      <detail>
        <line_number>265</line_number>
        <product_number_or_nmfc>7210-M-11.0</product_number_or_nmfc>
        <quantity>3</quantity>
      </detail>
      <detail>
        <line_number>266</line_number>
        <product_number_or_nmfc>7210-X-08.5</product_number_or_nmfc>
        <quantity>1</quantity>
      </detail>
      <detail>
        <line_number>267</line_number>
        <product_number_or_nmfc>7210-X-09.5</product_number_or_nmfc>
        <quantity>1</quantity>
      </detail>
      <detail>
        <line_number>268</line_number>
        <product_number_or_nmfc>7240-M-10.5</product_number_or_nmfc>
        <quantity>2</quantity>
      </detail>
      <detail>
        <line_number>269</line_number>
        <product_number_or_nmfc>7240-M-11.0</product_number_or_nmfc>
        <quantity>1</quantity>
      </detail>
      <detail>
        <line_number>270</line_number>
        <product_number_or_nmfc>7240-M-11.5</product_number_or_nmfc>
        <quantity>2</quantity>
      </detail>
      <detail>
        <line_number>271</line_number>
        <product_number_or_nmfc>7240-M-13.0</product_number_or_nmfc>
        <quantity>2</quantity>
      </detail>
      <detail>
        <line_number>272</line_number>
        <product_number_or_nmfc>7240-W-08.0</product_number_or_nmfc>
        <quantity>1</quantity>
      </detail>
      <detail>
        <line_number>273</line_number>
        <product_number_or_nmfc>7240-W-12.0</product_number_or_nmfc>
        <quantity>1</quantity>
      </detail>
      <detail>
        <line_number>274</line_number>
        <product_number_or_nmfc>7240-X-09.5</product_number_or_nmfc>
        <quantity>1</quantity>
      </detail>
      <detail>
        <line_number>275</line_number>
        <product_number_or_nmfc>7240-X-11.0</product_number_or_nmfc>
        <quantity>2</quantity>
      </detail>
      <detail>
        <line_number>276</line_number>
        <product_number_or_nmfc>7310-M-09.0</product_number_or_nmfc>
        <quantity>1</quantity>
      </detail>
      <detail>
        <line_number>277</line_number>
        <product_number_or_nmfc>7310-W-09.5</product_number_or_nmfc>
        <quantity>3</quantity>
      </detail>
      <detail>
        <line_number>278</line_number>
        <product_number_or_nmfc>7310-W-11.0</product_number_or_nmfc>
        <quantity>4</quantity>
      </detail>
      <detail>
        <line_number>279</line_number>
        <product_number_or_nmfc>7310-W-12.0</product_number_or_nmfc>
        <quantity>1</quantity>
      </detail>
      <detail>
        <line_number>280</line_number>
        <product_number_or_nmfc>7310-W-14.0</product_number_or_nmfc>
        <quantity>2</quantity>
      </detail>
      <detail>
        <line_number>281</line_number>
        <product_number_or_nmfc>7310-X-11.0</product_number_or_nmfc>
        <quantity>2</quantity>
      </detail>
      <detail>
        <line_number>282</line_number>
        <product_number_or_nmfc>7340-M-10.0</product_number_or_nmfc>
        <quantity>1</quantity>
      </detail>
      <detail>
        <line_number>283</line_number>
        <product_number_or_nmfc>7340-M-10.5</product_number_or_nmfc>
        <quantity>2</quantity>
      </detail>
      <detail>
        <line_number>284</line_number>
        <product_number_or_nmfc>7340-M-11.5</product_number_or_nmfc>
        <quantity>1</quantity>
      </detail>
      <detail>
        <line_number>285</line_number>
        <product_number_or_nmfc>7340-W-10.5</product_number_or_nmfc>
        <quantity>3</quantity>
      </detail>
      <detail>
        <line_number>286</line_number>
        <product_number_or_nmfc>7340-W-11.0</product_number_or_nmfc>
        <quantity>5</quantity>
      </detail>
      <detail>
        <line_number>287</line_number>
        <product_number_or_nmfc>7340-W-12.0</product_number_or_nmfc>
        <quantity>2</quantity>
      </detail>
      <detail>
        <line_number>288</line_number>
        <product_number_or_nmfc>7340-W-14.0</product_number_or_nmfc>
        <quantity>1</quantity>
      </detail>
      <detail>
        <line_number>289</line_number>
        <product_number_or_nmfc>7340-X-10.5</product_number_or_nmfc>
        <quantity>1</quantity>
      </detail>
      <detail>
        <line_number>290</line_number>
        <product_number_or_nmfc>7510-M-09.0</product_number_or_nmfc>
        <quantity>1</quantity>
      </detail>
      <detail>
        <line_number>291</line_number>
        <product_number_or_nmfc>7510-M-12.0</product_number_or_nmfc>
        <quantity>5</quantity>
      </detail>
      <detail>
        <line_number>292</line_number>
        <product_number_or_nmfc>7510-W-10.5</product_number_or_nmfc>
        <quantity>2</quantity>
      </detail>
      <detail>
        <line_number>293</line_number>
        <product_number_or_nmfc>7540-M-08.0</product_number_or_nmfc>
        <quantity>1</quantity>
      </detail>
      <detail>
        <line_number>294</line_number>
        <product_number_or_nmfc>7540-M-09.0</product_number_or_nmfc>
        <quantity>2</quantity>
      </detail>
      <detail>
        <line_number>295</line_number>
        <product_number_or_nmfc>7540-M-09.5</product_number_or_nmfc>
        <quantity>2</quantity>
      </detail>
      <detail>
        <line_number>296</line_number>
        <product_number_or_nmfc>7540-M-11.0</product_number_or_nmfc>
        <quantity>4</quantity>
      </detail>
      <detail>
        <line_number>297</line_number>
        <product_number_or_nmfc>7540-M-12.0</product_number_or_nmfc>
        <quantity>4</quantity>
      </detail>
      <detail>
        <line_number>298</line_number>
        <product_number_or_nmfc>7540-M-13.0</product_number_or_nmfc>
        <quantity>2</quantity>
      </detail>
      <detail>
        <line_number>299</line_number>
        <product_number_or_nmfc>7540-W-07.0</product_number_or_nmfc>
        <quantity>1</quantity>
      </detail>
      <detail>
        <line_number>300</line_number>
        <product_number_or_nmfc>7540-W-07.5</product_number_or_nmfc>
        <quantity>2</quantity>
      </detail>
      <detail>
        <line_number>301</line_number>
        <product_number_or_nmfc>7540-W-08.5</product_number_or_nmfc>
        <quantity>2</quantity>
      </detail>
      <detail>
        <line_number>302</line_number>
        <product_number_or_nmfc>7540-W-10.5</product_number_or_nmfc>
        <quantity>3</quantity>
      </detail>
      <detail>
        <line_number>303</line_number>
        <product_number_or_nmfc>7540-W-11.5</product_number_or_nmfc>
        <quantity>1</quantity>
      </detail>
      <detail>
        <line_number>304</line_number>
        <product_number_or_nmfc>7540-W-13.0</product_number_or_nmfc>
        <quantity>1</quantity>
      </detail>
      <detail>
        <line_number>305</line_number>
        <product_number_or_nmfc>7540-X-10.0</product_number_or_nmfc>
        <quantity>2</quantity>
      </detail>
      <detail>
        <line_number>306</line_number>
        <product_number_or_nmfc>7540-X-11.0</product_number_or_nmfc>
        <quantity>2</quantity>
      </detail>
      <detail>
        <line_number>307</line_number>
        <product_number_or_nmfc>7540-X-12.0</product_number_or_nmfc>
        <quantity>3</quantity>
      </detail>
      <detail>
        <line_number>308</line_number>
        <product_number_or_nmfc>7540-X-13.0</product_number_or_nmfc>
        <quantity>1</quantity>
      </detail>
      <detail>
        <line_number>309</line_number>
        <product_number_or_nmfc>7710-M-09.5</product_number_or_nmfc>
        <quantity>1</quantity>
      </detail>
      <detail>
        <line_number>310</line_number>
        <product_number_or_nmfc>7710-W-09.0</product_number_or_nmfc>
        <quantity>12</quantity>
      </detail>
      <detail>
        <line_number>311</line_number>
        <product_number_or_nmfc>7710-W-09.5</product_number_or_nmfc>
        <quantity>8</quantity>
      </detail>
      <detail>
        <line_number>312</line_number>
        <product_number_or_nmfc>7710-W-10.0</product_number_or_nmfc>
        <quantity>5</quantity>
      </detail>
      <detail>
        <line_number>313</line_number>
        <product_number_or_nmfc>7710-W-10.5</product_number_or_nmfc>
        <quantity>6</quantity>
      </detail>
      <detail>
        <line_number>314</line_number>
        <product_number_or_nmfc>7710-W-11.0</product_number_or_nmfc>
        <quantity>6</quantity>
      </detail>
      <detail>
        <line_number>315</line_number>
        <product_number_or_nmfc>7710-W-12.0</product_number_or_nmfc>
        <quantity>8</quantity>
      </detail>
      <detail>
        <line_number>316</line_number>
        <product_number_or_nmfc>7710-W-13.0</product_number_or_nmfc>
        <quantity>4</quantity>
      </detail>
      <detail>
        <line_number>317</line_number>
        <product_number_or_nmfc>7710-X-08.5</product_number_or_nmfc>
        <quantity>2</quantity>
      </detail>
      <detail>
        <line_number>318</line_number>
        <product_number_or_nmfc>7710-X-09.5</product_number_or_nmfc>
        <quantity>3</quantity>
      </detail>
      <detail>
        <line_number>319</line_number>
        <product_number_or_nmfc>7710-X-10.5</product_number_or_nmfc>
        <quantity>4</quantity>
      </detail>
      <detail>
        <line_number>320</line_number>
        <product_number_or_nmfc>7710-X-11.0</product_number_or_nmfc>
        <quantity>6</quantity>
      </detail>
      <detail>
        <line_number>321</line_number>
        <product_number_or_nmfc>7710-X-11.5</product_number_or_nmfc>
        <quantity>3</quantity>
      </detail>
      <detail>
        <line_number>322</line_number>
        <product_number_or_nmfc>7710-X-12.0</product_number_or_nmfc>
        <quantity>2</quantity>
      </detail>
      <detail>
        <line_number>323</line_number>
        <product_number_or_nmfc>7710-X-13.0</product_number_or_nmfc>
        <quantity>1</quantity>
      </detail>
      <detail>
        <line_number>324</line_number>
        <product_number_or_nmfc>7710-X-14.0</product_number_or_nmfc>
        <quantity>3</quantity>
      </detail>
      <detail>
        <line_number>325</line_number>
        <product_number_or_nmfc>7740-W-09.5</product_number_or_nmfc>
        <quantity>1</quantity>
      </detail>
      <detail>
        <line_number>326</line_number>
        <product_number_or_nmfc>7740-X-08.5</product_number_or_nmfc>
        <quantity>1</quantity>
      </detail>
      <detail>
        <line_number>327</line_number>
        <product_number_or_nmfc>7740-X-10.5</product_number_or_nmfc>
        <quantity>1</quantity>
      </detail>
      <detail>
        <line_number>328</line_number>
        <product_number_or_nmfc>8220-M-10.0</product_number_or_nmfc>
        <quantity>2</quantity>
      </detail>
      <detail>
        <line_number>329</line_number>
        <product_number_or_nmfc>8410-M-09.5</product_number_or_nmfc>
        <quantity>1</quantity>
      </detail>
      <detail>
        <line_number>330</line_number>
        <product_number_or_nmfc>9010-M-07.0</product_number_or_nmfc>
        <quantity>1</quantity>
      </detail>
      <detail>
        <line_number>331</line_number>
        <product_number_or_nmfc>9010-W-07.0</product_number_or_nmfc>
        <quantity>2</quantity>
      </detail>
      <detail>
        <line_number>332</line_number>
        <product_number_or_nmfc>9020-X-11.5</product_number_or_nmfc>
        <quantity>1</quantity>
      </detail>
      <detail>
        <line_number>333</line_number>
        <product_number_or_nmfc>9030-M-13.0</product_number_or_nmfc>
        <quantity>1</quantity>
      </detail>
      <detail>
        <line_number>334</line_number>
        <product_number_or_nmfc>9030-W-09.0</product_number_or_nmfc>
        <quantity>1</quantity>
      </detail>
      <detail>
        <line_number>335</line_number>
        <product_number_or_nmfc>9030-W-10.5</product_number_or_nmfc>
        <quantity>1</quantity>
      </detail>
      <detail>
        <line_number>336</line_number>
        <product_number_or_nmfc>9030-W-11.5</product_number_or_nmfc>
        <quantity>1</quantity>
      </detail>
      <detail>
        <line_number>337</line_number>
        <product_number_or_nmfc>9030-W-13.0</product_number_or_nmfc>
        <quantity>2</quantity>
      </detail>
      <detail>
        <line_number>338</line_number>
        <product_number_or_nmfc>9030-X-10.0</product_number_or_nmfc>
        <quantity>1</quantity>
      </detail>
      <detail>
        <line_number>339</line_number>
        <product_number_or_nmfc>9310-W-06.5</product_number_or_nmfc>
        <quantity>1</quantity>
      </detail>
      <detail>
        <line_number>340</line_number>
        <product_number_or_nmfc>9310-X-08.5</product_number_or_nmfc>
        <quantity>1</quantity>
      </detail>
      <detail>
        <line_number>341</line_number>
        <product_number_or_nmfc>9310-X-10.0</product_number_or_nmfc>
        <quantity>2</quantity>
      </detail>
      <detail>
        <line_number>342</line_number>
        <product_number_or_nmfc>9310-X-10.5</product_number_or_nmfc>
        <quantity>1</quantity>
      </detail>
      <detail>
        <line_number>343</line_number>
        <product_number_or_nmfc>9310-X-12.0</product_number_or_nmfc>
        <quantity>1</quantity>
      </detail>
      <detail>
        <line_number>344</line_number>
        <product_number_or_nmfc>9310-X-13.0</product_number_or_nmfc>
        <quantity>1</quantity>
      </detail>
      <detail>
        <line_number>345</line_number>
        <product_number_or_nmfc>9320-M-11.0</product_number_or_nmfc>
        <quantity>1</quantity>
      </detail>
      <detail>
        <line_number>346</line_number>
        <product_number_or_nmfc>9320-M-13.0</product_number_or_nmfc>
        <quantity>1</quantity>
      </detail>
      <detail>
        <line_number>347</line_number>
        <product_number_or_nmfc>9320-W-10.5</product_number_or_nmfc>
        <quantity>1</quantity>
      </detail>
      <detail>
        <line_number>348</line_number>
        <product_number_or_nmfc>9320-W-11.0</product_number_or_nmfc>
        <quantity>2</quantity>
      </detail>
      <detail>
        <line_number>349</line_number>
        <product_number_or_nmfc>9320-W-13.0</product_number_or_nmfc>
        <quantity>1</quantity>
      </detail>
      <detail>
        <line_number>350</line_number>
        <product_number_or_nmfc>9320-X-13.0</product_number_or_nmfc>
        <quantity>1</quantity>
      </detail>
      <detail>
        <line_number>351</line_number>
        <product_number_or_nmfc>9510-X-11.0</product_number_or_nmfc>
        <quantity>1</quantity>
      </detail>
      <detail>
        <line_number>352</line_number>
        <product_number_or_nmfc>9710-M-08.5</product_number_or_nmfc>
        <quantity>1</quantity>
      </detail>
      <detail>
        <line_number>353</line_number>
        <product_number_or_nmfc>9710-X-08.5</product_number_or_nmfc>
        <quantity>1</quantity>
      </detail>
      <detail>
        <line_number>354</line_number>
        <product_number_or_nmfc>9720-M-09.5</product_number_or_nmfc>
        <quantity>2</quantity>
      </detail>
      <detail>
        <line_number>355</line_number>
        <product_number_or_nmfc>9720-M-10.0</product_number_or_nmfc>
        <quantity>2</quantity>
      </detail>
      <detail>
        <line_number>356</line_number>
        <product_number_or_nmfc>9720-W-07.5</product_number_or_nmfc>
        <quantity>1</quantity>
      </detail>
      <detail>
        <line_number>357</line_number>
        <product_number_or_nmfc>9720-W-14.0</product_number_or_nmfc>
        <quantity>1</quantity>
      </detail>
      <detail>
        <line_number>358</line_number>
        <product_number_or_nmfc>9720-X-10.0</product_number_or_nmfc>
        <quantity>2</quantity>
      </detail>
      <detail>
        <line_number>359</line_number>
        <product_number_or_nmfc>9720-X-10.5</product_number_or_nmfc>
        <quantity>1</quantity>
      </detail>
      <detail>
        <line_number>360</line_number>
        <product_number_or_nmfc>9820-W-08.0</product_number_or_nmfc>
        <quantity>2</quantity>
      </detail>
      <detail>
        <line_number>361</line_number>
        <product_number_or_nmfc>9820-W-11.0</product_number_or_nmfc>
        <quantity>1</quantity>
      </detail>
      <detail>
        <line_number>362</line_number>
        <product_number_or_nmfc>9820-X-12.0</product_number_or_nmfc>
        <quantity>2</quantity>
      </detail>
      <detail>
        <line_number>363</line_number>
        <product_number_or_nmfc>9820-X-13.0</product_number_or_nmfc>
        <quantity>1</quantity>
      </detail>
      <detail>
        <line_number>364</line_number>
        <product_number_or_nmfc>5610-M-09.0-P7</product_number_or_nmfc>
        <quantity>1</quantity>
      </detail>
      <detail>
        <line_number>365</line_number>
        <product_number_or_nmfc>5610-M-09.5-P4</product_number_or_nmfc>
        <quantity>1</quantity>
      </detail>
      <detail>
        <line_number>366</line_number>
        <product_number_or_nmfc>5610-M-15.0-P6</product_number_or_nmfc>
        <quantity>1</quantity>
      </detail>
      <detail>
        <line_number>367</line_number>
        <product_number_or_nmfc>5610-W-07.5-P2</product_number_or_nmfc>
        <quantity>1</quantity>
      </detail>
      <detail>
        <line_number>368</line_number>
        <product_number_or_nmfc>5610-W-08.0-P1</product_number_or_nmfc>
        <quantity>1</quantity>
      </detail>
      <detail>
        <line_number>369</line_number>
        <product_number_or_nmfc>5610-W-10.0-P2</product_number_or_nmfc>
        <quantity>1</quantity>
      </detail>
      <detail>
        <line_number>370</line_number>
        <product_number_or_nmfc>5610-W-11.5-P1</product_number_or_nmfc>
        <quantity>1</quantity>
      </detail>
      <detail>
        <line_number>371</line_number>
        <product_number_or_nmfc>5610-W-13.0-P4</product_number_or_nmfc>
        <quantity>1</quantity>
      </detail>
      <detail>
        <line_number>372</line_number>
        <product_number_or_nmfc>5610-X-11.0-P1</product_number_or_nmfc>
        <quantity>1</quantity>
      </detail>
      <detail>
        <line_number>373</line_number>
        <product_number_or_nmfc>6210-M-07.5-P4</product_number_or_nmfc>
        <quantity>1</quantity>
      </detail>
      <detail>
        <line_number>374</line_number>
        <product_number_or_nmfc>6210-M-10.0-P1</product_number_or_nmfc>
        <quantity>1</quantity>
      </detail>
      <detail>
        <line_number>375</line_number>
        <product_number_or_nmfc>6210-M-11.5-P2</product_number_or_nmfc>
        <quantity>1</quantity>
      </detail>
      <detail>
        <line_number>376</line_number>
        <product_number_or_nmfc>6210-M-12.0-P1</product_number_or_nmfc>
        <quantity>1</quantity>
      </detail>
      <detail>
        <line_number>377</line_number>
        <product_number_or_nmfc>6210-W-08.5-P2</product_number_or_nmfc>
        <quantity>1</quantity>
      </detail>
      <detail>
        <line_number>378</line_number>
        <product_number_or_nmfc>6210-W-10.0-P1</product_number_or_nmfc>
        <quantity>1</quantity>
      </detail>
      <detail>
        <line_number>379</line_number>
        <product_number_or_nmfc>6210-X-07.5-P1</product_number_or_nmfc>
        <quantity>1</quantity>
      </detail>
      <detail>
        <line_number>380</line_number>
        <product_number_or_nmfc>8210-W-08.0-P7</product_number_or_nmfc>
        <quantity>1</quantity>
      </detail>
      <detail>
        <line_number>381</line_number>
        <product_number_or_nmfc>8210-W-08.5-P8</product_number_or_nmfc>
        <quantity>1</quantity>
      </detail>
      <detail>
        <line_number>382</line_number>
        <product_number_or_nmfc>8220-M-06.5-P8</product_number_or_nmfc>
        <quantity>1</quantity>
      </detail>
      <detail>
        <line_number>383</line_number>
        <product_number_or_nmfc>8220-M-08.0-P8</product_number_or_nmfc>
        <quantity>1</quantity>
      </detail>
      <detail>
        <line_number>384</line_number>
        <product_number_or_nmfc>8220-M-10.5-P8</product_number_or_nmfc>
        <quantity>1</quantity>
      </detail>
      <detail>
        <line_number>385</line_number>
        <product_number_or_nmfc>8220-W-09.0-P8</product_number_or_nmfc>
        <quantity>1</quantity>
      </detail>
      <detail>
        <line_number>386</line_number>
        <product_number_or_nmfc>8220-W-10.0-P8</product_number_or_nmfc>
        <quantity>1</quantity>
      </detail>
      <detail>
        <line_number>387</line_number>
        <product_number_or_nmfc>8220-X-08.0-P8</product_number_or_nmfc>
        <quantity>1</quantity>
      </detail>
      <detail>
        <line_number>388</line_number>
        <product_number_or_nmfc>8410-W-07.0-P6</product_number_or_nmfc>
        <quantity>1</quantity>
      </detail>
      <detail>
        <line_number>389</line_number>
        <product_number_or_nmfc>8420-M-09.5-P7</product_number_or_nmfc>
        <quantity>1</quantity>
      </detail>
    </order_detail>
  </warehouse_shipping_order>
</warehouse_shipping_orders>